{"output": [{"id": 0, "box": [606, 25, 721, 39], "linking": [[0, 1], [0, 2], [0, 3]], "label": "v"}, {"id": 1, "box": [560, 28, 584, 35], "linking": [[1, 0], [1, 2]], "label": "k"}, {"id": 2, "box": [313, 39, 562, 51], "linking": [[2, 0], [2, 1], [2, 5]], "label": "other"}, {"id": 3, "box": [259, 54, 617, 70], "linking": [[3, 0], [3, 4], [3, 5], [3, 9]], "label": "other"}, {"id": 4, "box": [329, 100, 381, 110], "linking": [[4, 3], [4, 5], [4, 9]], "label": "k"}, {"id": 5, "box": [396, 112, 626, 128], "linking": [[5, 2], [5, 3], [5, 4], [5, 6], [5, 7], [5, 8], [5, 9], [5, 19]], "label": "v"}, {"id": 6, "box": [328, 112, 367, 125], "linking": [[6, 5], [6, 9]], "label": "k"}, {"id": 7, "box": [668, 112, 734, 128], "linking": [[7, 5]], "label": "v"}, {"id": 8, "box": [104, 114, 157, 128], "linking": [[8, 5], [8, 9], [8, 10]], "label": "k"}, {"id": 9, "box": [200, 115, 253, 128], "linking": [[9, 3], [9, 4], [9, 5], [9, 6], [9, 8], [9, 10]], "label": "v"}, {"id": 10, "box": [104, 155, 706, 168], "linking": [[10, 8], [10, 9], [10, 11], [10, 12], [10, 13], [10, 14], [10, 15], [10, 16], [10, 17]], "label": "k"}, {"id": 11, "box": [146, 209, 706, 221], "linking": [[11, 10], [11, 12], [11, 14], [11, 25]], "label": "v"}, {"id": 12, "box": [112, 221, 720, 235], "linking": [[12, 10], [12, 11], [12, 13], [12, 14], [12, 25], [12, 26]], "label": "v"}, {"id": 13, "box": [110, 237, 706, 250], "linking": [[13, 10], [13, 12], [13, 14], [13, 25], [13, 26]], "label": "v"}, {"id": 14, "box": [112, 251, 706, 263], "linking": [[14, 10], [14, 11], [14, 12], [14, 13], [14, 15], [14, 16], [14, 17], [14, 18], [14, 25], [14, 26], [14, 31]], "label": "v"}, {"id": 15, "box": [112, 265, 720, 278], "linking": [[15, 10], [15, 14], [15, 16], [15, 25], [15, 26]], "label": "v"}, {"id": 16, "box": [114, 279, 700, 290], "linking": [[16, 10], [16, 14], [16, 15], [16, 17], [16, 18], [16, 25], [16, 26], [16, 31]], "label": "v"}, {"id": 17, "box": [112, 293, 665, 307], "linking": [[17, 10], [17, 14], [17, 16], [17, 18], [17, 25], [17, 26]], "label": "v"}, {"id": 18, "box": [112, 306, 517, 318], "linking": [[18, 14], [18, 16], [18, 17], [18, 19]], "label": "v"}, {"id": 19, "box": [364, 346, 495, 360], "linking": [[19, 5], [19, 18]], "label": "other"}, {"id": 20, "box": [103, 440, 282, 456], "linking": [[20, 21], [20, 22], [20, 23], [20, 27], [20, 30]], "label": "k"}, {"id": 21, "box": [165, 458, 539, 478], "linking": [[21, 20], [21, 23], [21, 24], [21, 25], [21, 26], [21, 31], [21, 38]], "label": "v"}, {"id": 22, "box": [165, 474, 623, 492], "linking": [[22, 20], [22, 23], [22, 24], [22, 25], [22, 26], [22, 31]], "label": "v"}, {"id": 23, "box": [165, 487, 329, 503], "linking": [[23, 20], [23, 21], [23, 22], [23, 24], [23, 25], [23, 26], [23, 31], [23, 35], [23, 37], [23, 38]], "label": "v"}, {"id": 24, "box": [104, 517, 245, 529], "linking": [[24, 21], [24, 22], [24, 23], [24, 25], [24, 26], [24, 27], [24, 28], [24, 29], [24, 30], [24, 31]], "label": "k"}, {"id": 25, "box": [139, 529, 712, 548], "linking": [[25, 11], [25, 12], [25, 13], [25, 14], [25, 15], [25, 16], [25, 17], [25, 21], [25, 22], [25, 23], [25, 24], [25, 27], [25, 28], [25, 29], [25, 30]], "label": "other"}, {"id": 26, "box": [104, 542, 724, 564], "linking": [[26, 12], [26, 13], [26, 14], [26, 15], [26, 16], [26, 17], [26, 21], [26, 22], [26, 23], [26, 24], [26, 27], [26, 28], [26, 29], [26, 30]], "label": "other"}, {"id": 27, "box": [103, 559, 257, 571], "linking": [[27, 20], [27, 24], [27, 25], [27, 26], [27, 28], [27, 29], [27, 30], [27, 31], [27, 33], [27, 35], [27, 37], [27, 38], [27, 41]], "label": "v"}, {"id": 28, "box": [139, 570, 704, 589], "linking": [[28, 24], [28, 25], [28, 26], [28, 27], [28, 29], [28, 30], [28, 31], [28, 33], [28, 38]], "label": "v"}, {"id": 29, "box": [104, 583, 698, 604], "linking": [[29, 24], [29, 25], [29, 26], [29, 27], [29, 28], [29, 30], [29, 31], [29, 33], [29, 35], [29, 37], [29, 38], [29, 41]], "label": "v"}, {"id": 30, "box": [104, 598, 251, 614], "linking": [[30, 20], [30, 24], [30, 25], [30, 26], [30, 27], [30, 28], [30, 29], [30, 31], [30, 33], [30, 35], [30, 37], [30, 38], [30, 41], [30, 44], [30, 46], [30, 51], [30, 54]], "label": "v"}, {"id": 31, "box": [135, 612, 745, 625], "linking": [[31, 14], [31, 16], [31, 21], [31, 22], [31, 23], [31, 24], [31, 27], [31, 28], [31, 29], [31, 30], [31, 32], [31, 33], [31, 34], [31, 35], [31, 37], [31, 38], [31, 41], [31, 42]], "label": "other"}, {"id": 32, "box": [468, 636, 726, 654], "linking": [[32, 31], [32, 33], [32, 34], [32, 36], [32, 38], [32, 39]], "label": "v"}, {"id": 33, "box": [104, 642, 198, 653], "linking": [[33, 27], [33, 28], [33, 29], [33, 30], [33, 31], [33, 32], [33, 34], [33, 38]], "label": "k"}, {"id": 34, "box": [245, 643, 289, 654], "linking": [[34, 31], [34, 32], [34, 33], [34, 35], [34, 38], [34, 47]], "label": "v"}, {"id": 35, "box": [134, 656, 353, 668], "linking": [[35, 23], [35, 27], [35, 29], [35, 30], [35, 31], [35, 34], [35, 37], [35, 38]], "label": "k"}, {"id": 36, "box": [468, 667, 534, 679], "linking": [[36, 32], [36, 38]], "label": "k"}, {"id": 37, "box": [106, 671, 225, 683], "linking": [[37, 23], [37, 27], [37, 29], [37, 30], [37, 31], [37, 35], [37, 38]], "label": "k"}, {"id": 38, "box": [259, 671, 354, 684], "linking": [[38, 21], [38, 23], [38, 27], [38, 28], [38, 29], [38, 30], [38, 31], [38, 32], [38, 33], [38, 34], [38, 35], [38, 36], [38, 37], [38, 39], [38, 40], [38, 41], [38, 42], [38, 44], [38, 47], [38, 50]], "label": "k"}, {"id": 39, "box": [468, 696, 547, 708], "linking": [[39, 32], [39, 38], [39, 40], [39, 42]], "label": "k"}, {"id": 40, "box": [607, 696, 679, 710], "linking": [[40, 38], [40, 39], [40, 55]], "label": "v"}, {"id": 41, "box": [104, 698, 190, 712], "linking": [[41, 27], [41, 29], [41, 30], [41, 31], [41, 38], [41, 42]], "label": "k"}, {"id": 42, "box": [235, 698, 343, 712], "linking": [[42, 31], [42, 38], [42, 39], [42, 41], [42, 47]], "label": "v"}, {"id": 43, "box": [482, 726, 548, 736], "linking": [[43, 45]], "label": "k"}, {"id": 44, "box": [107, 729, 190, 738], "linking": [[44, 30], [44, 38]], "label": "k"}, {"id": 45, "box": [484, 754, 534, 765], "linking": [[45, 43], [45, 48]], "label": "k"}, {"id": 46, "box": [104, 768, 232, 782], "linking": [[46, 30], [46, 47]], "label": "k"}, {"id": 47, "box": [254, 770, 296, 781], "linking": [[47, 34], [47, 38], [47, 42], [47, 46], [47, 48], [47, 50]], "label": "other"}, {"id": 48, "box": [587, 780, 750, 792], "linking": [[48, 45], [48, 47], [48, 49], [48, 55]], "label": "v"}, {"id": 49, "box": [468, 781, 520, 795], "linking": [[49, 48]], "label": "k"}, {"id": 50, "box": [262, 802, 376, 847], "linking": [[50, 38], [50, 47], [50, 51], [50, 52]], "label": "v"}, {"id": 51, "box": [106, 814, 198, 825], "linking": [[51, 30], [51, 50]], "label": "k"}, {"id": 52, "box": [468, 823, 506, 840], "linking": [[52, 50], [52, 53]], "label": "k"}, {"id": 53, "box": [600, 825, 754, 840], "linking": [[53, 52], [53, 55]], "label": "v"}, {"id": 54, "box": [104, 854, 254, 866], "linking": [[54, 30]], "label": "k"}, {"id": 55, "box": [604, 868, 692, 885], "linking": [[55, 40], [55, 48], [55, 53]], "label": "other"}], "faster_rcnn_scores": [0.9504469037055969, 0.856066882610321, -1.0, -1.0, 0.8901588916778564, 0.8791376352310181, 0.93841153383255, 0.8465443849563599, 0.962647557258606, 0.6600998640060425, 0.6578887701034546, 0.7667491436004639, 0.7667491436004639, 0.7667491436004639, 0.7667491436004639, 0.7667491436004639, 0.7667491436004639, 0.7667491436004639, 0.7667491436004639, 0.5960396528244019, 0.8613914251327515, 0.6757567524909973, 0.6757567524909973, 0.6757567524909973, 0.8321300148963928, -1.0, -1.0, 0.5746756196022034, 0.5746756196022034, 0.5746756196022034, 0.5746756196022034, -1.0, 0.6928306221961975, 0.9343140721321106, 0.6097617149353027, 0.9072971343994141, 0.6986871957778931, 0.9322197437286377, 0.6810635328292847, 0.8303217887878418, 0.7481316328048706, 0.9778467416763306, 0.8351156115531921, 0.8533139824867249, 0.9713548421859741, 0.8566786646842957, 0.8143696188926697, -1.0, 0.960289716720581, 0.8453688025474548, 0.5742858648300171, 0.9432738423347473, 0.7603164315223694, 0.852903425693512, 0.9280062913894653, -1.0], "siamese_scores": {"0": [0.9486368894577026, 0.9107635617256165, 0.7425574064254761], "1": [0.9486368894577026, 0.8259251713752747], "2": [0.9107635617256165, 0.8259251713752747, 0.7243821024894714], "3": [0.7425574064254761, 0.5305740833282471, 0.5692131519317627, 0.9259678721427917], "4": [0.5305740833282471, 0.8962109684944153, 0.5723421573638916], "5": [0.7243821024894714, 0.5692131519317627, 0.8962109684944153, 0.9746689200401306, 0.5898101329803467, 0.8493512868881226, 0.5263913869857788, 0.5082932710647583], "6": [0.9746689200401306, 0.8859450817108154], "7": [0.5898101329803467], "8": [0.8493512868881226, 0.9104263186454773, 0.8426014184951782], "9": [0.9259678721427917, 0.5723421573638916, 0.5263913869857788, 0.8859450817108154, 0.9104263186454773, 0.9076315760612488], "10": [0.8426014184951782, 0.9076315760612488, 0.6970018148422241, 0.8533269762992859, 0.8377516865730286, 0.9167320728302002, 0.7638707160949707, 0.7009947896003723, 0.6882811784744263], "11": [0.6970018148422241, 0.5557006001472473, 0.6573739051818848, 0.6200499534606934], "12": [0.8533269762992859, 0.5557006001472473, 0.5092859268188477, 0.7277388572692871, 0.5276004672050476, 0.5541629195213318], "13": [0.8377516865730286, 0.5092859268188477, 0.8738642930984497, 0.5822614431381226, 0.6367964744567871], "14": [0.9167320728302002, 0.6573739051818848, 0.7277388572692871, 0.8738642930984497, 0.8177695274353027, 0.7568771243095398, 0.6438194513320923, 0.5231590270996094, 0.8148664832115173, 0.8426372408866882, 0.7024319767951965], "15": [0.7638707160949707, 0.8177695274353027, 0.5326923131942749, 0.5641002655029297, 0.6763286590576172], "16": [0.7009947896003723, 0.7568771243095398, 0.5326923131942749, 0.5077543258666992, 0.5192338228225708, 0.6864426732063293, 0.7069020867347717, 0.506689727306366], "17": [0.6882811784744263, 0.6438194513320923, 0.5077543258666992, 0.6982943415641785, 0.583293616771698, 0.6662331223487854], "18": [0.5231590270996094, 0.5192338228225708, 0.6982943415641785, 0.7121471166610718], "19": [0.5082932710647583, 0.7121471166610718], "20": [0.8842645883560181, 0.8426903486251831, 0.8958945870399475, 0.6305117607116699, 0.7030211687088013], "21": [0.8842645883560181, 0.8288779854774475, 0.7626006007194519, 0.786460280418396, 0.7687625885009766, 0.5112617611885071, 0.5503209233283997], "22": [0.8426903486251831, 0.955323338508606, 0.9201613068580627, 0.8754245042800903, 0.8400070071220398, 0.7223098874092102], "23": [0.8958945870399475, 0.8288779854774475, 0.955323338508606, 0.9823211431503296, 0.9947993755340576, 0.9848015904426575, 0.7122049927711487, 0.5986480116844177, 0.514018714427948, 0.9198938608169556], "24": [0.7626006007194519, 0.9201613068580627, 0.9823211431503296, 0.9925116300582886, 0.9873108863830566, 0.894639790058136, 0.8988549709320068, 0.9642397165298462, 0.9230585098266602, 0.6329087018966675], "25": [0.6200499534606934, 0.5276004672050476, 0.5822614431381226, 0.8148664832115173, 0.5641002655029297, 0.6864426732063293, 0.583293616771698, 0.786460280418396, 0.8754245042800903, 0.9947993755340576, 0.9925116300582886, 0.9935160875320435, 0.9493069648742676, 0.9815788269042969, 0.9813108444213867], "26": [0.5541629195213318, 0.6367964744567871, 0.8426372408866882, 0.6763286590576172, 0.7069020867347717, 0.6662331223487854, 0.7687625885009766, 0.8400070071220398, 0.9848015904426575, 0.9873108863830566, 0.99808669090271, 0.9617664813995361, 0.98406583070755, 0.9859288334846497], "27": [0.6305117607116699, 0.894639790058136, 0.9935160875320435, 0.99808669090271, 0.8728519082069397, 0.9338729381561279, 0.618729293346405, 0.9738773107528687, 0.6155796647071838, 0.5323458909988403, 0.6474973559379578, 0.7471269369125366, 0.5002697110176086], "28": [0.8988549709320068, 0.9493069648742676, 0.9617664813995361, 0.8728519082069397, 0.8541475534439087, 0.9223110675811768, 0.9347230792045593, 0.7784857153892517, 0.5733900666236877], "29": [0.9642397165298462, 0.9815788269042969, 0.98406583070755, 0.9338729381561279, 0.8541475534439087, 0.939526379108429, 0.9936953186988831, 0.9561312794685364, 0.8229767680168152, 0.83999103307724, 0.972337543964386, 0.5260156989097595], "30": [0.7030211687088013, 0.9230585098266602, 0.9813108444213867, 0.9859288334846497, 0.618729293346405, 0.9223110675811768, 0.939526379108429, 0.9996640682220459, 0.8203777074813843, 0.7510311007499695, 0.8585450649261475, 0.9833523035049438, 0.6934109330177307, 0.6702411770820618, 0.6791834831237793, 0.5254809260368347, 0.7291024327278137], "31": [0.7024319767951965, 0.506689727306366, 0.5112617611885071, 0.7223098874092102, 0.7122049927711487, 0.6329087018966675, 0.9738773107528687, 0.9347230792045593, 0.9936953186988831, 0.9996640682220459, 0.8574422001838684, 0.9634550213813782, 0.980810821056366, 0.8781585693359375, 0.8159684538841248, 0.9683148264884949, 0.6006370186805725, 0.6389157772064209], "32": [0.8574422001838684, 0.6290441751480103, 0.5542361736297607, 0.8379917740821838, 0.9769262671470642, 0.5025424957275391], "33": [0.6155796647071838, 0.7784857153892517, 0.9561312794685364, 0.8203777074813843, 0.9634550213813782, 0.6290441751480103, 0.8677054047584534, 0.9098620414733887], "34": [0.980810821056366, 0.5542361736297607, 0.8677054047584534, 0.510211706161499, 0.996450662612915, 0.8301857113838196], "35": [0.5986480116844177, 0.5323458909988403, 0.8229767680168152, 0.7510311007499695, 0.8781585693359375, 0.510211706161499, 0.5492610335350037, 0.9727810621261597], "36": [0.8379917740821838, 0.9869186282157898], "37": [0.514018714427948, 0.6474973559379578, 0.83999103307724, 0.8585450649261475, 0.8159684538841248, 0.5492610335350037, 0.9903963804244995], "38": [0.5503209233283997, 0.9198938608169556, 0.7471269369125366, 0.5733900666236877, 0.972337543964386, 0.9833523035049438, 0.9683148264884949, 0.9769262671470642, 0.9098620414733887, 0.996450662612915, 0.9727810621261597, 0.9869186282157898, 0.9903963804244995, 0.8690829873085022, 0.9280222058296204, 0.9226493835449219, 0.9955435395240784, 0.6575952172279358, 0.9513221979141235, 0.933481752872467], "39": [0.5025424957275391, 0.8690829873085022, 0.802666962146759, 0.5334078073501587], "40": [0.9280222058296204, 0.802666962146759, 0.7897412776947021], "41": [0.5002697110176086, 0.5260156989097595, 0.6934109330177307, 0.6006370186805725, 0.9226493835449219, 0.8355256915092468], "42": [0.6389157772064209, 0.9955435395240784, 0.5334078073501587, 0.8355256915092468, 0.8578216433525085], "43": [0.5115927457809448], "44": [0.6702411770820618, 0.6575952172279358], "45": [0.5115927457809448, 0.7213184833526611], "46": [0.6791834831237793, 0.9015173316001892], "47": [0.8301857113838196, 0.9513221979141235, 0.8578216433525085, 0.9015173316001892, 0.8935054540634155, 0.9535567760467529], "48": [0.7213184833526611, 0.8935054540634155, 0.9603599905967712, 0.8964833617210388], "49": [0.9603599905967712], "50": [0.933481752872467, 0.9535567760467529, 0.5224002599716187, 0.5808601379394531], "51": [0.5254809260368347, 0.5224002599716187], "52": [0.5808601379394531, 0.9795073866844177], "53": [0.9795073866844177, 0.9063578248023987], "54": [0.7291024327278137], "55": [0.7897412776947021, 0.8964833617210388, 0.9063578248023987]}}